LICENCE
LICENSE.txt
README.md
setup.py
googlewifi/__init__.py
googlewifi.egg-info/PKG-INFO
googlewifi.egg-info/SOURCES.txt
googlewifi.egg-info/dependency_links.txt
googlewifi.egg-info/requires.txt
googlewifi.egg-info/top_level.txt