Metadata-Version: 2.1
Name: googlewifi
Version: 0.0.21
Summary: Google WiFi API wrapper for integration to Google Wifi systems.
Home-page: https://github.com/djtimca/googlewifi-api
Author: Tim Empringham
Author-email: tim.empringham@live.ca
License: apache-2.0
Download-URL: https://github.com/djtimca/googlewifi-api/archive/v_0.0.21.tar.gz
Keywords: Google,Wifi
Platform: UNKNOWN
Classifier: Development Status :: 3 - Alpha
Classifier: Intended Audience :: Developers
Classifier: Topic :: Software Development :: Build Tools
Classifier: License :: OSI Approved :: Apache Software License
Classifier: Programming Language :: Python :: 3
Classifier: Programming Language :: Python :: 3.4
Classifier: Programming Language :: Python :: 3.5
Classifier: Programming Language :: Python :: 3.6
Requires-Python: >=3.8
License-File: LICENCE
License-File: LICENSE.txt
